promisify_dmsbilas.py
promisify_dmsbilas-0.0.3.dist-info/METADATA
promisify_dmsbilas-0.0.3.dist-info/WHEEL
promisify_dmsbilas-0.0.3.dist-info/licenses/LICENSE
promisify_dmsbilas-0.0.3.dist-info/RECORD
